epython/__init__.py
epython/environment.py
epython/filters.py
epython/handlers.py
epython/logger.py
epython/network.py
epython/ssh.py
epython/errors/__init__.py
epython/errors/base.py
epython/errors/filters.py
epython/errors/network.py
epython/errors/poke.py
epython/errors/ssh.py
epython/errors/util.py
epython/poke/__init__.py
epython/poke/eprequests.py
epython/poke/processors.py
elibs_epython-2021.1045.dist-info/LICENSE
elibs_epython-2021.1045.dist-info/METADATA
elibs_epython-2021.1045.dist-info/WHEEL
elibs_epython-2021.1045.dist-info/top_level.txt
elibs_epython-2021.1045.dist-info/RECORD
