Metadata-Version: 2.1
Name: elibs-epython
Version: 2021.1045
Summary: A set of modules that help with QA
Home-page: https://github.com/elibs/epython
Author: Ray Gomez
Author-email: codenomad@gmail.com
License: UNKNOWN
Project-URL: Bug Tracker, https://github.com/elibs/epython/issues
Platform: UNKNOWN
Classifier: Programming Language :: Python :: 3
Classifier: License :: OSI Approved :: MIT License
Classifier: Operating System :: OS Independent
Requires-Python: >=3.6
Requires-Dist: paramiko
Requires-Dist: requests
Requires-Dist: scp
